Metadata-Version: 1.0
Name: openvino-kaggle
Version: 1.0.0
Summary: OpenVINO toolkit package for Kaggle Notebooks
Home-page: UNKNOWN
Author: Muhammad Ali
Author-email: malirashid1994@gmail.com
License: UNKNOWN
Platform: UNKNOWN
